{"@context":"https://schema.org","@id":"https://dev.fysiodouma.nl/wiki/ziekte-van-bechterew/#webPage","@type":"MedicalWebPage","about":{"@id":"https://dev.fysiodouma.nl/wiki/ziekte-van-bechterew/#wiki","@type":"MedicalCondition","alternateName":["spondylitis ankylopoetica"],"code":{"@type":"MedicalCode","codeValue":9631008,"codingSystem":"SNOMED-CT"},"description":"De ziekte van Bechterew is een ontstekingsziekte die pijn en stijfheid in de ruggengraat, het bekken en andere gewrichten, zoals heup, knieën, voeten en schouders veroorzaakt. De ziekte van Bechterew is een chronisch (levenslange) ziekte en is erfelijk. Hoewel de meerderheid van mensen met de ziekte van Bechterew een gen genaamd HLA-B27 dragen, ontwikkelt ongeveer 80% van de mensen die het gen van een ouder met de ziekte van Bechterew hebben geërfd de ziekte niet.","name":"Ziekte van Bechterew","sameAs":null,"signOrSymptom":[{"@type":"MedicalSignOrSymptom","code":{"@type":"MedicalCode","codeValue":"279039007","codingSystem":"SNOMED-CT"},"name":"Lage rugpijn"},{"@type":"MedicalSignOrSymptom","code":{"@type":"MedicalCode","codeValue":"202487003","codingSystem":"SNOMED-CT"},"name":"Pijn in SI gewricht"},{"@type":"MedicalSignOrSymptom","code":{"@type":"MedicalCode","codeValue":"49218002","codingSystem":"SNOMED-CT"},"name":"Heuppijn"},{"@type":"MedicalSignOrSymptom","code":{"@type":"MedicalCode","codeValue":"45326000","codingSystem":"SNOMED-CT"},"name":"Schouderpijn"},{"@type":"MedicalSignOrSymptom","code":{"@type":"MedicalCode","codeValue":"386661006","codingSystem":"SNOMED-CT"},"name":"Koorts"}]},"accountablePerson":{"@id":"https://www.fysiodouma.nl/frank/#person","@type":"Person","name":"Frank Mulder"},"author":{"@id":"https://www.fysiodouma.nl/frank/#person","@type":"Person","name":"Frank Mulder"},"copyrightHolder":{"@id":"https://www.fysiodouma.nl/frank/#person","@type":"Person","name":"Frank Mulder"},"copyrightYear":"2016","creator":{"@id":"https://www.fysiodouma.nl/frank/#person","@type":"Person","name":"Frank Mulder"},"dateModified":"2016-12-04T16:30:16Z","datePublished":"2016-12-04T16:30:16Z","description":"De ziekte van Bechterew is een ontstekingsziekte die pijn en stijfheid in de ruggengraat, het bekken en andere gewrichten, zoals heup, knieën, voeten en schouders veroorzaakt. De ziekte van Bechterew is een chronisch (levenslange) ziekte en is erfelijk. Hoewel de meerderheid van mensen met de ziekte van Bechterew een gen genaamd HLA-B27 dragen, ontwikkelt ongeveer 80% van de mensen die het gen van een ouder met de ziekte van Bechterew hebben geërfd de ziekte niet.","inLanguage":"nl","mainEntityOfPage":{"@id":"https://dev.fysiodouma.nl/wiki/ziekte-van-bechterew/","@type":"MedicalWebPage"},"publisher":{"@type":"Organization","logo":{"@type":"ImageObject","height":1e3,"url":"https://www.fysiodouma.nl/images/logos/logo-fysiodouma-1000x1000.png","width":1e3},"name":"Fysiotherapie Douma"},"speakable":{"@type":"SpeakableSpecification","cssSelector":"intro"}}